adversarial_nets/__init__.py
adversarial_nets/data/__init__.py
adversarial_nets/data/data.py
adversarial_nets/estimator/__init__.py
adversarial_nets/estimator/estimator.py
adversarial_nets/generator/__init__.py
adversarial_nets/generator/generator.py
adversarial_nets/utils/__init__.py
adversarial_nets/utils/utils.py
adversarial_nets_lib_econ-0.1.3.dist-info/licenses/LICENSE
adversarial_nets_lib_econ-0.1.3.dist-info/METADATA
adversarial_nets_lib_econ-0.1.3.dist-info/WHEEL
adversarial_nets_lib_econ-0.1.3.dist-info/top_level.txt
adversarial_nets_lib_econ-0.1.3.dist-info/RECORD
