Metadata-Version: 2.4
Name: adversarial-nets-lib-econ
Version: 0.1.3
Summary: Adversarial estimator for structural models on graphs
Author: VitaIll
License: MIT License
Requires-Python: >=3.8
License-File: LICENSE
Requires-Dist: numpy>=1.21.0
Requires-Dist: networkx>=2.6.0
Requires-Dist: matplotlib>=3.4.0
Requires-Dist: scikit-optimize>=0.9.0
Requires-Dist: tqdm>=4.62.0
Requires-Dist: scipy>=1.7.0
Requires-Dist: torch>=2.0.0
Requires-Dist: torch-geometric>=2.3.0
Requires-Dist: scikit-learn>=1.0
Requires-Dist: optuna>=3.0.0
Dynamic: license-file
